odoo10_addon_packaging_uom_view-10.0.1.0.1-py3.8-nspkg.pth
odoo/addons/packaging_uom_view/README.rst
odoo/addons/packaging_uom_view/__init__.py
odoo/addons/packaging_uom_view/__manifest__.py
odoo/addons/packaging_uom_view/i18n/packaging_uom_view.pot
odoo/addons/packaging_uom_view/readme/CONTRIBUTORS.rst
odoo/addons/packaging_uom_view/readme/DESCRIPTION.rst
odoo/addons/packaging_uom_view/readme/USAGE.rst
odoo/addons/packaging_uom_view/static/description/icon.png
odoo/addons/packaging_uom_view/static/description/index.html
odoo/addons/packaging_uom_view/views/product_template.xml
odoo10_addon_packaging_uom_view-10.0.1.0.1.dist-info/METADATA
odoo10_addon_packaging_uom_view-10.0.1.0.1.dist-info/WHEEL
odoo10_addon_packaging_uom_view-10.0.1.0.1.dist-info/namespace_packages.txt
odoo10_addon_packaging_uom_view-10.0.1.0.1.dist-info/top_level.txt
odoo10_addon_packaging_uom_view-10.0.1.0.1.dist-info/RECORD
